[
    {
        "id": 1,
        "eventID": 2,
        "sender": "dynann@email.com",
        "feedback": {
            "experienceRating": null,
            "favoritePart": null,
            "venueFeedback": null,
            "topicsRelevant": null,
            "favoriteSpeaker": null,
            "organizationRating": null,
            "registrationFeedback": null,
            "networkingOpportunities": null,
            "futureSuggestions": null,
            "additionalComments": null
        }
    }
]